frccontrol/__init__.py
frccontrol/ctrlutil.py
frccontrol/discretization.py
frccontrol/extended_kalman_filter.py
frccontrol/kalman_filter.py
frccontrol/linear_plant_inversion_feedforward.py
frccontrol/linear_quadratic_regulator.py
frccontrol/models.py
frccontrol/numerical_integration.py
frccontrol/numerical_jacobian.py
frccontrol/plotutil.py
frccontrol/profiles.py
frccontrol/trajectory.py
frccontrol/version.py
frccontrol/test/__init__.py
frccontrol/test/test_numerical_jacobian.py
frccontrol-2025.6.dist-info/licenses/LICENSE.txt
frccontrol-2025.6.dist-info/METADATA
frccontrol-2025.6.dist-info/WHEEL
frccontrol-2025.6.dist-info/top_level.txt
frccontrol-2025.6.dist-info/RECORD
