Metadata-Version: 2.4
Name: frccontrol
Version: 2025.6
Summary: Provides SciPy wrappers for easing development of state-space models for the FIRST Robotics Competition
Author-email: Tyler Veness <calcmogul@gmail.com>
License: BSD-3-Clause
Project-URL: Homepage, https://github.com/calcmogul/frccontrol
Classifier: Development Status :: 5 - Production/Stable
Classifier: Intended Audience :: Developers
Classifier: Intended Audience :: Education
Classifier: License :: OSI Approved :: BSD License
Classifier: Operating System :: OS Independent
Classifier: Topic :: Scientific/Engineering
Classifier: Programming Language :: Python :: 3
License-File: LICENSE.txt
Requires-Dist: matplotlib
Requires-Dist: numpy
Requires-Dist: scipy
Dynamic: license-file
